tile_tools/__init__.py
tile_tools/common/__init__.py
tile_tools/common/set.py
tile_tools/common/types.py
tile_tools/coords.py
tile_tools/cover/README.md
tile_tools/cover/__init__.py
tile_tools/cover/gj.py
tile_tools/cover/indexes.py
tile_tools/cover/tiles.py
tile_tools/distance.py
tile_tools/settings.py
tile_tools/tilebelt/README.md
tile_tools/tilebelt/__init__.py
tile_tools/tilebelt/bbox.py
tile_tools/tilebelt/gj.py
tile_tools/tilebelt/point.py
tile_tools/tilebelt/quadkey.py
tile_tools/tilebelt/traverse.py
tile_tools-0.1.2.dist-info/LICENSE
tile_tools-0.1.2.dist-info/WHEEL
tile_tools-0.1.2.dist-info/METADATA
tile_tools-0.1.2.dist-info/RECORD
