Metadata-Version: 2.1
Name: tile-tools
Version: 0.1.2
Summary: A collection of tools for navigating Mapbox tiles.
License: MIT
Author: Joe Nudell
Author-email: jnu@stanford.edu
Requires-Python: >=3.10,<3.12
Classifier: License :: OSI Approved :: MIT License
Classifier: Programming Language :: Python :: 3
Classifier: Programming Language :: Python :: 3.10
Classifier: Programming Language :: Python :: 3.11
Requires-Dist: geojson (>=2.5.0,<3.0.0)
Requires-Dist: mercantile (>=1.2.1,<2.0.0)
